pacspeddbase-0.2.dist-info/METADATA
pacspeddbase-0.2.dist-info/WHEEL
pacspeddbase/__init__.py
pacspeddbase/pacspeddbase.cpython-312-aarch64-linux-gnu.so
pacspeddbase-0.2.dist-info/RECORD
